LICENSE
README.md
lyyliutongz.py
setup.py
lyyliutongz.egg-info/PKG-INFO
lyyliutongz.egg-info/SOURCES.txt
lyyliutongz.egg-info/dependency_links.txt
lyyliutongz.egg-info/top_level.txt