Metadata-Version: 2.1
Name: lyyliutongz
Version: 1.4
Summary: lyy stock tdx liutongz for lyy
Author: yy
Author-email: 
License: MIT
License-File: LICENSE
